ops_academy/__init__.py
ops_academy/core.py
ops_academy-0.0.1.dist-info/METADATA
ops_academy-0.0.1.dist-info/WHEEL
ops_academy-0.0.1.dist-info/RECORD
