Metadata-Version: 2.4
Name: ops-academy
Version: 0.0.1
Requires-Dist: fasttext
Requires-Dist: numpy<2.0
